thecompaniesapi/__init__.py
thecompaniesapi/sdk.py
thecompaniesapi/generated/__init__.py
thecompaniesapi/generated/models.py
thecompaniesapi/generated/operations_map.py
thecompaniesapi-1.0.2.dist-info/METADATA
thecompaniesapi-1.0.2.dist-info/WHEEL
thecompaniesapi-1.0.2.dist-info/licenses/LICENSE
thecompaniesapi-1.0.2.dist-info/RECORD
