Metadata-Version: 2.4
Name: thecompaniesapi
Version: 1.0.2
Summary: Python SDK for The Companies API
Project-URL: Homepage, https://www.thecompaniesapi.com/
Project-URL: Docs, https://www.thecompaniesapi.com/api
Author-email: The Companies API SARL <yael@thecompaniesapi.com>
License-File: LICENSE
Classifier: License :: OSI Approved :: MIT License
Classifier: Operating System :: OS Independent
Classifier: Programming Language :: Python :: 3
Requires-Python: >=3.9
Requires-Dist: requests>=2.28.1
Requires-Dist: urllib3>=1.26.0
Provides-Extra: codegen
Requires-Dist: datamodel-code-generator[http]>=0.21.0; extra == 'codegen'
Requires-Dist: pydantic>=2.0.0; extra == 'codegen'
Provides-Extra: test
Requires-Dist: pytest-mock>=3.0; extra == 'test'
Requires-Dist: pytest>=6.0; extra == 'test'
Requires-Dist: python-dotenv>=0.19.0; extra == 'test'
Requires-Dist: responses>=0.20.0; extra == 'test'
